httpcodes/__init__.py
httpcodes-1.0.0.dist-info/LICENSE
httpcodes-1.0.0.dist-info/METADATA
httpcodes-1.0.0.dist-info/WHEEL
httpcodes-1.0.0.dist-info/top_level.txt
httpcodes-1.0.0.dist-info/RECORD
